Metadata-Version: 2.1
Name: regbuild
Version: 1.0.8
Summary: make regular show
Author: gadapokasoz6
